<?xml version="1.0" encoding="UTF-8"?>
<resources>
    <string name="app.cart">点击此页面顶部的此按钮将商品加入购物车。</string>
    <string name="app.describe">这里是发现美妙家居家具的最佳去处，让您的家更美丽。</string>
    <string name="app.get_started">立即开始！</string>
    <string name="app.greetings">欢迎!</string>
    <string name="app.header">让您的家更加美丽</string>
    <string name="app.product.description">这款支架由天然木材制成。设计非常简洁，极简风格。这确实是任何家庭最好的家具之一。有3种不同的颜色可供选择，您可以轻松选择最适合您家的颜色。</string>
    <string name="app.product.title">极简主义！</string>
    <string name="app.rating_value">4.5</string>
    <string name="app.reviews">{{count}} 评价</string>
</resources>
